trifusionviz/__init__.py
trifusionviz/recappels.py
trifusionviz/trifusionviz.py
trifusionviz-0.7.1.data/scripts/tfv
trifusionviz-0.7.1.dist-info/METADATA
trifusionviz-0.7.1.dist-info/WHEEL
trifusionviz-0.7.1.dist-info/top_level.txt
trifusionviz-0.7.1.dist-info/RECORD
