Metadata-Version: 2.1
Name: trifusionviz
Version: 0.7.1
Summary: illustration du tri fusion
Home-page: https://github.com/cobacdavid/trifusionviz
Author: David COBAC
Author-email: david.cobac@gmail.com
License: CC-BY-NC-SA
Keywords: merge sort,sort,tri,tri fusion,graphviz
Platform: UNKNOWN
Requires-Python: >3.5
Requires-Dist: graphviz
